TiRank/Dataloader.py
TiRank/GPextractor.py
TiRank/Imageprocessing.py
TiRank/LoadData.py
TiRank/Loss.py
TiRank/Model.py
TiRank/SCSTpreprocess.py
TiRank/TrainPre.py
TiRank/Visualization.py
TiRank/__init__.py
TiRank/ctran.py
TiRank/main.py
TiRank-0.7.dist-info/LICENSE
TiRank-0.7.dist-info/METADATA
TiRank-0.7.dist-info/WHEEL
TiRank-0.7.dist-info/top_level.txt
TiRank-0.7.dist-info/RECORD
