Metadata-Version: 2.1
Name: TiRank
Version: 0.7
Summary: A comprehensive analysis tool for transfering phenotype of bulk transcritomic data to single cell or spatial transcriptomic data.
Home-page: https://github.com/LenisLin/TiRank
Author: Lenis Lin
Author-email: 727682308@qq.com
License: MIT License
Classifier: Programming Language :: Python :: 3
Classifier: License :: OSI Approved :: MIT License
Requires-Python: >=3.9
License-File: LICENSE
Requires-Dist: torch
Requires-Dist: torchvision
Requires-Dist: optuna==3.4.0
Requires-Dist: numpy==1.22.3
Requires-Dist: scipy==1.8.1
Requires-Dist: pandas==1.5.3
Requires-Dist: leidenalg
Requires-Dist: scikit-learn==1.0.2
Requires-Dist: lifelines==0.27.8
Requires-Dist: statsmodels==0.14.0
Requires-Dist: imbalanced-learn==0.11.0
Requires-Dist: matplotlib==3.7.1
Requires-Dist: seaborn==0.12.2
Requires-Dist: pillow==9.4.0
Requires-Dist: scanpy==1.9.5
Requires-Dist: gseapy==1.1.1
Requires-Dist: dash==2.14.2
Requires-Dist: dash-bootstrap-components==1.5.0
Requires-Dist: dash-loading-spinners==1.0.3
